<mods xmlns="http://www.loc.gov/mods/v3" xmlns:exslt="http://exslt.org/common" xmlns:xsi="http://www.w3.org/2001/XMLSchema-instance" xmlns:xlink="http://www.w3.org/1999/xlink" xsi:schemaLocation="http://www.loc.gov/mods/v3 http://www.loc.gov/standards/mods/v3/mods-3-3.xsd" version="3.3" ID="P0b002ee1817974c3">
<name type="corporate">
 <namePart>United States Government Printing Office</namePart>
 <role>
  <roleTerm type="text" authority="marcrelator">printer</roleTerm>
  <roleTerm type="code" authority="marcrelator">prt</roleTerm>
</role>
 <role>
  <roleTerm type="text" authority="marcrelator">distributor</roleTerm>
  <roleTerm type="code" authority="marcrelator">dst</roleTerm>
</role>
</name>
<name type="corporate">
 <namePart>United States</namePart>
 <namePart>United States District Court District of Nebraska</namePart>
 <role>
  <roleTerm type="text" authority="marcrelator">author</roleTerm>
  <roleTerm type="code" authority="marcrelator">aut</roleTerm>
</role>
 <description>Government Organization</description>
</name>
<typeOfResource>text</typeOfResource>
<genre authority="marcgt">government publication</genre>
<language>
 <languageTerm authority="iso639-2b" type="code">eng</languageTerm>
</language>
<extension>
 <collectionCode>USCOURTS</collectionCode>
 <category>Judicial Publications</category>
 <branch>judicial</branch>
 <dateIngested>2012-01-13</dateIngested>
</extension>
<originInfo>
 <publisher>Administrative Office of the United States Courts</publisher>
 <dateIssued encoding="w3cdtf">2011-01-25</dateIssued>
 <issuance>monographic</issuance>
</originInfo>
<physicalDescription>
 <note type="source content type">deposited</note>
 <digitalOrigin>born digital</digitalOrigin>
</physicalDescription>
<classification authority="sudocs">JU 4.15</classification>
<identifier type="uri">http://www.gpo.gov/fdsys/pkg/USCOURTS-ned-8_09-cv-00195</identifier>
<identifier type="local">P0b002ee1817974c3</identifier>
<recordInfo>
 <recordContentSource authority="marcorg">DGPO</recordContentSource>
 <recordCreationDate encoding="w3cdtf">2012-01-13</recordCreationDate>
 <recordChangeDate encoding="w3cdtf">2012-01-13</recordChangeDate>
 <recordIdentifier source="DGPO">USCOURTS-ned-8_09-cv-00195</recordIdentifier>
 <recordOrigin>machine generated</recordOrigin>
 <languageOfCataloging>
  <languageTerm authority="iso639-2b" type="code">eng</languageTerm>
</languageOfCataloging>
</recordInfo>
<accessCondition type="GPO scope determination">fdlp</accessCondition>
<extension>
 <docClass>USCOURTS</docClass>
 <accessId>USCOURTS-ned-8_09-cv-00195</accessId>
 <courtType>District</courtType>
 <courtCode>ned</courtCode>
 <courtCircuit>8th</courtCircuit>
 <courtState>Nebraska</courtState>
 <courtSortOrder>2300</courtSortOrder>
 <caseNumber>8:09-cv-00195</caseNumber>
 <caseOffice>8 Omaha</caseOffice>
 <caseType>civil</caseType>
 <natureSuitCode>190</natureSuitCode>
 <natureSuit>Other Contract Actions</natureSuit>
 <cause>28:1332 Diversity-Other Contract</cause>
 <party fullName="Applied Industrial Technologies, Inc." lastName="Applied Industrial Technologies, Inc." role="Interested Party"></party>
 <party fullName="DXP Enterprises, Inc." lastName="DXP Enterprises, Inc." role="Plaintiff"></party>
 <party fullName="Precision Industries, Inc." lastName="Precision Industries, Inc." role="Counter Defendant"></party>
 <party fullName="Precision Industries, Inc." lastName="Precision Industries, Inc." role="Plaintiff"></party>
 <party fullName="Tyson Foods, Inc." lastName="Tyson Foods, Inc." role="Counter Claimant"></party>
 <party fullName="Tyson Foods, Inc." lastName="Tyson Foods, Inc." role="Defendant"></party>
</extension>
<titleInfo>
 <title>Precision Industries, Inc. v. Tyson Foods, Inc.</title>
 <partNumber>8:09-cv-00195</partNumber>
</titleInfo>
<location>
 <url access="object in context" displayLabel="Content Detail">http://www.gpo.gov/fdsys/pkg/USCOURTS-ned-8_09-cv-00195/content-detail.html</url>
</location>
<classification authority="sudocs">JU 4.15</classification>
<identifier type="preferred citation">8:09-cv-00195;09-195</identifier>
<name type="corporate">
 <namePart>United States District Court District of Nebraska</namePart>
 <namePart>8th Circuit</namePart>
 <namePart>8 Omaha</namePart>
 <affiliation>U.S. Courts</affiliation>
 <role>
  <roleTerm authority="marcrelator" type="text">author</roleTerm>
  <roleTerm authority="marcrelator" type="code">aut</roleTerm>
</role>
</name>
<name type="personal">
 <displayForm>Applied Industrial Technologies, Inc.</displayForm>
 <namePart type="family">Applied Industrial Technologies, Inc.</namePart>
 <namePart type="given"></namePart>
 <namePart type="termsOfAddress"></namePart>
 <description>Interested Party</description>
</name>
<name type="personal">
 <displayForm>DXP Enterprises, Inc.</displayForm>
 <namePart type="family">DXP Enterprises, Inc.</namePart>
 <namePart type="given"></namePart>
 <namePart type="termsOfAddress"></namePart>
 <description>Plaintiff</description>
</name>
<name type="personal">
 <displayForm>Precision Industries, Inc.</displayForm>
 <namePart type="family">Precision Industries, Inc.</namePart>
 <namePart type="given"></namePart>
 <namePart type="termsOfAddress"></namePart>
 <description>Counter Defendant</description>
</name>
<name type="personal">
 <displayForm>Precision Industries, Inc.</displayForm>
 <namePart type="family">Precision Industries, Inc.</namePart>
 <namePart type="given"></namePart>
 <namePart type="termsOfAddress"></namePart>
 <description>Plaintiff</description>
</name>
<name type="personal">
 <displayForm>Tyson Foods, Inc.</displayForm>
 <namePart type="family">Tyson Foods, Inc.</namePart>
 <namePart type="given"></namePart>
 <namePart type="termsOfAddress"></namePart>
 <description>Counter Claimant</description>
</name>
<name type="personal">
 <displayForm>Tyson Foods, Inc.</displayForm>
 <namePart type="family">Tyson Foods, Inc.</namePart>
 <namePart type="given"></namePart>
 <namePart type="termsOfAddress"></namePart>
 <description>Defendant</description>
</name>
<extension>
 <docClass>USCOURTS</docClass>
 <accessId>USCOURTS-ned-8_09-cv-00195</accessId>
 <courtType>District</courtType>
 <courtCode>ned</courtCode>
 <courtCircuit>8th</courtCircuit>
 <courtState>Nebraska</courtState>
 <courtSortOrder>2300</courtSortOrder>
 <caseNumber>8:09-cv-00195</caseNumber>
 <caseOffice>8 Omaha</caseOffice>
 <caseType>civil</caseType>
 <natureSuitCode>190</natureSuitCode>
 <natureSuit>Other Contract Actions</natureSuit>
 <cause>28:1332 Diversity-Other Contract</cause>
 <party fullName="Applied Industrial Technologies, Inc." lastName="Applied Industrial Technologies, Inc." role="Interested Party"></party>
 <party fullName="DXP Enterprises, Inc." lastName="DXP Enterprises, Inc." role="Plaintiff"></party>
 <party fullName="Precision Industries, Inc." lastName="Precision Industries, Inc." role="Counter Defendant"></party>
 <party fullName="Precision Industries, Inc." lastName="Precision Industries, Inc." role="Plaintiff"></party>
 <party fullName="Tyson Foods, Inc." lastName="Tyson Foods, Inc." role="Counter Claimant"></party>
 <party fullName="Tyson Foods, Inc." lastName="Tyson Foods, Inc." role="Defendant"></party>
 <state>Nebraska</state>
</extension>
<relatedItem type="constituent" ID="id-USCOURTS-ned-8_09-cv-00195-0" xlink:href="http://www.gpo.gov/fdsys/granule/USCOURTS-ned-8_09-cv-00195/USCOURTS-ned-8_09-cv-00195-0/mods.xml">
 <titleInfo>
  <title>Precision Industries, Inc. v. Tyson Foods, Inc.</title>
  <subTitle>ORDER granting 24 Motion to Extend; the deadline for filing a reply brief in support of its motion to dismiss is extended until and including October 2, 2009. Ordered by Chief Judge Joseph F. Bataillon. (CJP)</subTitle>
  <partNumber>0</partNumber>
</titleInfo>
 <originInfo>
  <dateIssued>2009-09-28</dateIssued>
</originInfo>
 <relatedItem xlink:href="http://www.gpo.gov/fdsys/pkg/pdf/USCOURTS-ned-8_09-cv-00195-0.pdf" type="otherFormat">
  <identifier type="FDsys Unique ID">D09002ee1817fca16</identifier>
</relatedItem>
 <identifier type="uri">http://www.gpo.gov/fdsys/granule/USCOURTS-ned-8_09-cv-00195/USCOURTS-ned-8_09-cv-00195-0</identifier>
 <identifier type="former granule identifier">ned-8_09-cv-00195_0.pdf</identifier>
 <location>
  <url access="object in context" displayLabel="Content Detail">http://www.gpo.gov/fdsys/granule/USCOURTS-ned-8_09-cv-00195/USCOURTS-ned-8_09-cv-00195-0/content-detail.html</url>
  <url access="raw object" displayLabel="PDF rendition">http://www.gpo.gov/fdsys/pkg/USCOURTS-ned-8_09-cv-00195/pdf/USCOURTS-ned-8_09-cv-00195-0.pdf</url>
</location>
 <extension>
  <searchTitle>USCOURTS 8:09-cv-00195; Precision Industries, Inc. v. Tyson Foods, Inc.; </searchTitle>
  <courtName>United States District Court District of Nebraska</courtName>
  <state>Nebraska</state>
  <accessId>USCOURTS-ned-8_09-cv-00195-0</accessId>
  <sequenceNumber>0</sequenceNumber>
  <dateIssued>2009-09-28</dateIssued>
  <docketText>ORDER granting 24 Motion to Extend; the deadline for filing a reply brief in support of its motion to dismiss is extended until and including October 2, 2009. Ordered by Chief Judge Joseph F. Bataillon. (CJP)</docketText>
</extension>
</relatedItem>
<relatedItem type="constituent" ID="id-USCOURTS-ned-8_09-cv-00195-1" xlink:href="http://www.gpo.gov/fdsys/granule/USCOURTS-ned-8_09-cv-00195/USCOURTS-ned-8_09-cv-00195-1/mods.xml">
 <titleInfo>
  <title>Precision Industries, Inc. v. Tyson Foods, Inc.</title>
  <subTitle>MEMORANDUM AND ORDER granting 15 the Defendant&apos;s Motion to Dismiss the plaintiff&apos;s first cause of action. Ordered by Chief Judge Joseph F. Bataillon. (MKR)</subTitle>
  <partNumber>1</partNumber>
</titleInfo>
 <originInfo>
  <dateIssued>2009-11-25</dateIssued>
</originInfo>
 <relatedItem xlink:href="http://www.gpo.gov/fdsys/pkg/pdf/USCOURTS-ned-8_09-cv-00195-1.pdf" type="otherFormat">
  <identifier type="FDsys Unique ID">D09002ee1817fca17</identifier>
</relatedItem>
 <identifier type="uri">http://www.gpo.gov/fdsys/granule/USCOURTS-ned-8_09-cv-00195/USCOURTS-ned-8_09-cv-00195-1</identifier>
 <identifier type="former granule identifier">ned-8_09-cv-00195_1.pdf</identifier>
 <location>
  <url access="object in context" displayLabel="Content Detail">http://www.gpo.gov/fdsys/granule/USCOURTS-ned-8_09-cv-00195/USCOURTS-ned-8_09-cv-00195-1/content-detail.html</url>
  <url access="raw object" displayLabel="PDF rendition">http://www.gpo.gov/fdsys/pkg/USCOURTS-ned-8_09-cv-00195/pdf/USCOURTS-ned-8_09-cv-00195-1.pdf</url>
</location>
 <extension>
  <searchTitle>USCOURTS 8:09-cv-00195; Precision Industries, Inc. v. Tyson Foods, Inc.; </searchTitle>
  <courtName>United States District Court District of Nebraska</courtName>
  <state>Nebraska</state>
  <accessId>USCOURTS-ned-8_09-cv-00195-1</accessId>
  <sequenceNumber>1</sequenceNumber>
  <dateIssued>2009-11-25</dateIssued>
  <docketText>MEMORANDUM AND ORDER granting 15 the Defendant&apos;s Motion to Dismiss the plaintiff&apos;s first cause of action. Ordered by Chief Judge Joseph F. Bataillon. (MKR)</docketText>
</extension>
</relatedItem>
<relatedItem type="constituent" ID="id-USCOURTS-ned-8_09-cv-00195-2" xlink:href="http://www.gpo.gov/fdsys/granule/USCOURTS-ned-8_09-cv-00195/USCOURTS-ned-8_09-cv-00195-2/mods.xml">
 <titleInfo>
  <title>Precision Industries, Inc. v. Tyson Foods, Inc.</title>
  <subTitle>ORDER granting 34 Joint Stipulation for Protective Order. Ordered by Magistrate Judge Thomas D. Thalken. (PCV, )</subTitle>
  <partNumber>2</partNumber>
</titleInfo>
 <originInfo>
  <dateIssued>2009-12-28</dateIssued>
</originInfo>
 <relatedItem xlink:href="http://www.gpo.gov/fdsys/pkg/pdf/USCOURTS-ned-8_09-cv-00195-2.pdf" type="otherFormat">
  <identifier type="FDsys Unique ID">D09002ee1817fca19</identifier>
</relatedItem>
 <identifier type="uri">http://www.gpo.gov/fdsys/granule/USCOURTS-ned-8_09-cv-00195/USCOURTS-ned-8_09-cv-00195-2</identifier>
 <identifier type="former granule identifier">ned-8_09-cv-00195_2.pdf</identifier>
 <location>
  <url access="object in context" displayLabel="Content Detail">http://www.gpo.gov/fdsys/granule/USCOURTS-ned-8_09-cv-00195/USCOURTS-ned-8_09-cv-00195-2/content-detail.html</url>
  <url access="raw object" displayLabel="PDF rendition">http://www.gpo.gov/fdsys/pkg/USCOURTS-ned-8_09-cv-00195/pdf/USCOURTS-ned-8_09-cv-00195-2.pdf</url>
</location>
 <extension>
  <searchTitle>USCOURTS 8:09-cv-00195; Precision Industries, Inc. v. Tyson Foods, Inc.; </searchTitle>
  <courtName>United States District Court District of Nebraska</courtName>
  <state>Nebraska</state>
  <accessId>USCOURTS-ned-8_09-cv-00195-2</accessId>
  <sequenceNumber>2</sequenceNumber>
  <dateIssued>2009-12-28</dateIssued>
  <docketText>ORDER granting 34 Joint Stipulation for Protective Order. Ordered by Magistrate Judge Thomas D. Thalken. (PCV, )</docketText>
</extension>
</relatedItem>
<relatedItem type="constituent" ID="id-USCOURTS-ned-8_09-cv-00195-3" xlink:href="http://www.gpo.gov/fdsys/granule/USCOURTS-ned-8_09-cv-00195/USCOURTS-ned-8_09-cv-00195-3/mods.xml">
 <titleInfo>
  <title>Precision Industries, Inc. v. Tyson Foods, Inc.</title>
  <subTitle>ORDER - The plaintiff&apos;s motion to compel 42 is granted. Tyson Foods, Inc. shall supplement its responses for Interrogatories Nos. 4 and 5 on or before May 7, 2010. ADMONITION Pursuant to NECivR 72.2 any appeal of this Order shall be filed with the Clerk of the Court within fourteen (14) days after being served with a copy of this Order. Failure to timely appeal may constitute a waiver of any objection to the Order. The brief in support of any appeal shall be filed at the time of filing such appeal. Failure to file a brief in support of any appeal may be deemed an abandonment of the appeal. Ordered by Magistrate Judge Thomas D. Thalken. (KBJ)</subTitle>
  <partNumber>3</partNumber>
</titleInfo>
 <originInfo>
  <dateIssued>2010-04-20</dateIssued>
</originInfo>
 <relatedItem xlink:href="http://www.gpo.gov/fdsys/pkg/pdf/USCOURTS-ned-8_09-cv-00195-3.pdf" type="otherFormat">
  <identifier type="FDsys Unique ID">D09002ee1817fca18</identifier>
</relatedItem>
 <identifier type="uri">http://www.gpo.gov/fdsys/granule/USCOURTS-ned-8_09-cv-00195/USCOURTS-ned-8_09-cv-00195-3</identifier>
 <identifier type="former granule identifier">ned-8_09-cv-00195_3.pdf</identifier>
 <location>
  <url access="object in context" displayLabel="Content Detail">http://www.gpo.gov/fdsys/granule/USCOURTS-ned-8_09-cv-00195/USCOURTS-ned-8_09-cv-00195-3/content-detail.html</url>
  <url access="raw object" displayLabel="PDF rendition">http://www.gpo.gov/fdsys/pkg/USCOURTS-ned-8_09-cv-00195/pdf/USCOURTS-ned-8_09-cv-00195-3.pdf</url>
</location>
 <extension>
  <searchTitle>USCOURTS 8:09-cv-00195; Precision Industries, Inc. v. Tyson Foods, Inc.; </searchTitle>
  <courtName>United States District Court District of Nebraska</courtName>
  <state>Nebraska</state>
  <accessId>USCOURTS-ned-8_09-cv-00195-3</accessId>
  <sequenceNumber>3</sequenceNumber>
  <dateIssued>2010-04-20</dateIssued>
  <docketText>ORDER - The plaintiff&apos;s motion to compel 42 is granted. Tyson Foods, Inc. shall supplement its responses for Interrogatories Nos. 4 and 5 on or before May 7, 2010. ADMONITION Pursuant to NECivR 72.2 any appeal of this Order shall be filed with the Clerk of the Court within fourteen (14) days after being served with a copy of this Order. Failure to timely appeal may constitute a waiver of any objection to the Order. The brief in support of any appeal shall be filed at the time of filing such appeal. Failure to file a brief in support of any appeal may be deemed an abandonment of the appeal. Ordered by Magistrate Judge Thomas D. Thalken. (KBJ)</docketText>
</extension>
</relatedItem>
<relatedItem type="constituent" ID="id-USCOURTS-ned-8_09-cv-00195-4" xlink:href="http://www.gpo.gov/fdsys/granule/USCOURTS-ned-8_09-cv-00195/USCOURTS-ned-8_09-cv-00195-4/mods.xml">
 <titleInfo>
  <title>Precision Industries, Inc. v. Tyson Foods, Inc.</title>
  <subTitle>AMENDED ORDER SETTING FINAL PROGRESSION OF CASE - The Joint Motion to amend 58 is granted. The Deposition deadline is set for 10/29/2010. The Final Pretrial Conference is set for 11/23/2010 at 2:00pm in chambers of the undersigned Magistrate Judge. Trial is set to commence, at the court&apos;s call, 12,13/2010 before Chief Judge Joseph F. Bataillon. Ordered by Magistrate Judge Thomas D. Thalken. (KBJ)</subTitle>
  <partNumber>4</partNumber>
</titleInfo>
 <originInfo>
  <dateIssued>2010-04-29</dateIssued>
</originInfo>
 <relatedItem xlink:href="http://www.gpo.gov/fdsys/pkg/pdf/USCOURTS-ned-8_09-cv-00195-4.pdf" type="otherFormat">
  <identifier type="FDsys Unique ID">D09002ee1817fcac1</identifier>
</relatedItem>
 <identifier type="uri">http://www.gpo.gov/fdsys/granule/USCOURTS-ned-8_09-cv-00195/USCOURTS-ned-8_09-cv-00195-4</identifier>
 <identifier type="former granule identifier">ned-8_09-cv-00195_4.pdf</identifier>
 <location>
  <url access="object in context" displayLabel="Content Detail">http://www.gpo.gov/fdsys/granule/USCOURTS-ned-8_09-cv-00195/USCOURTS-ned-8_09-cv-00195-4/content-detail.html</url>
  <url access="raw object" displayLabel="PDF rendition">http://www.gpo.gov/fdsys/pkg/USCOURTS-ned-8_09-cv-00195/pdf/USCOURTS-ned-8_09-cv-00195-4.pdf</url>
</location>
 <extension>
  <searchTitle>USCOURTS 8:09-cv-00195; Precision Industries, Inc. v. Tyson Foods, Inc.; </searchTitle>
  <courtName>United States District Court District of Nebraska</courtName>
  <state>Nebraska</state>
  <accessId>USCOURTS-ned-8_09-cv-00195-4</accessId>
  <sequenceNumber>4</sequenceNumber>
  <dateIssued>2010-04-29</dateIssued>
  <docketText>AMENDED ORDER SETTING FINAL PROGRESSION OF CASE - The Joint Motion to amend 58 is granted. The Deposition deadline is set for 10/29/2010. The Final Pretrial Conference is set for 11/23/2010 at 2:00pm in chambers of the undersigned Magistrate Judge. Trial is set to commence, at the court&apos;s call, 12,13/2010 before Chief Judge Joseph F. Bataillon. Ordered by Magistrate Judge Thomas D. Thalken. (KBJ)</docketText>
</extension>
</relatedItem>
<relatedItem type="constituent" ID="id-USCOURTS-ned-8_09-cv-00195-5" xlink:href="http://www.gpo.gov/fdsys/granule/USCOURTS-ned-8_09-cv-00195/USCOURTS-ned-8_09-cv-00195-5/mods.xml">
 <titleInfo>
  <title>Precision Industries, Inc. v. Tyson Foods, Inc.</title>
  <subTitle>SECOND AMENDED ORDER FOR PROGRESSION OF CASE - This matter is before the court on the parties&apos; Joint Motion to Amend the Progression Order 75. The motion is granted, in part. The Final Pretrial conference is set before the undersigned magistrate judge on March 18, 2010 at 11:00am in chambers. Trial is set to commence, at the court&apos;s call, April 18, 2010, in Omaha, Nebraska, before the Honorable Joseph F. Bataillon and a jury. Ordered by Magistrate Judge Thomas D. Thalken. (KBJ)</subTitle>
  <partNumber>5</partNumber>
</titleInfo>
 <originInfo>
  <dateIssued>2010-07-28</dateIssued>
</originInfo>
 <relatedItem xlink:href="http://www.gpo.gov/fdsys/pkg/pdf/USCOURTS-ned-8_09-cv-00195-5.pdf" type="otherFormat">
  <identifier type="FDsys Unique ID">D09002ee1817fca15</identifier>
</relatedItem>
 <identifier type="uri">http://www.gpo.gov/fdsys/granule/USCOURTS-ned-8_09-cv-00195/USCOURTS-ned-8_09-cv-00195-5</identifier>
 <identifier type="former granule identifier">ned-8_09-cv-00195_5.pdf</identifier>
 <location>
  <url access="object in context" displayLabel="Content Detail">http://www.gpo.gov/fdsys/granule/USCOURTS-ned-8_09-cv-00195/USCOURTS-ned-8_09-cv-00195-5/content-detail.html</url>
  <url access="raw object" displayLabel="PDF rendition">http://www.gpo.gov/fdsys/pkg/USCOURTS-ned-8_09-cv-00195/pdf/USCOURTS-ned-8_09-cv-00195-5.pdf</url>
</location>
 <extension>
  <searchTitle>USCOURTS 8:09-cv-00195; Precision Industries, Inc. v. Tyson Foods, Inc.; </searchTitle>
  <courtName>United States District Court District of Nebraska</courtName>
  <state>Nebraska</state>
  <accessId>USCOURTS-ned-8_09-cv-00195-5</accessId>
  <sequenceNumber>5</sequenceNumber>
  <dateIssued>2010-07-28</dateIssued>
  <docketText>SECOND AMENDED ORDER FOR PROGRESSION OF CASE - This matter is before the court on the parties&apos; Joint Motion to Amend the Progression Order 75. The motion is granted, in part. The Final Pretrial conference is set before the undersigned magistrate judge on March 18, 2010 at 11:00am in chambers. Trial is set to commence, at the court&apos;s call, April 18, 2010, in Omaha, Nebraska, before the Honorable Joseph F. Bataillon and a jury. Ordered by Magistrate Judge Thomas D. Thalken. (KBJ)</docketText>
</extension>
</relatedItem>
<relatedItem type="constituent" ID="id-USCOURTS-ned-8_09-cv-00195-6" xlink:href="http://www.gpo.gov/fdsys/granule/USCOURTS-ned-8_09-cv-00195/USCOURTS-ned-8_09-cv-00195-6/mods.xml">
 <titleInfo>
  <title>Precision Industries, Inc. v. Tyson Foods, Inc.</title>
  <subTitle>ORDER granting 72 Motion to Compel; adopting 89 Stipulation. The defendant shall have until October 1, 2010, to supplement discovery responses. Ordered by Magistrate Judge Thomas D. Thalken. (TRL)</subTitle>
  <partNumber>6</partNumber>
</titleInfo>
 <originInfo>
  <dateIssued>2010-09-13</dateIssued>
</originInfo>
 <relatedItem xlink:href="http://www.gpo.gov/fdsys/pkg/pdf/USCOURTS-ned-8_09-cv-00195-6.pdf" type="otherFormat">
  <identifier type="FDsys Unique ID">D09002ee1817fca1b</identifier>
</relatedItem>
 <identifier type="uri">http://www.gpo.gov/fdsys/granule/USCOURTS-ned-8_09-cv-00195/USCOURTS-ned-8_09-cv-00195-6</identifier>
 <identifier type="former granule identifier">ned-8_09-cv-00195_6.pdf</identifier>
 <location>
  <url access="object in context" displayLabel="Content Detail">http://www.gpo.gov/fdsys/granule/USCOURTS-ned-8_09-cv-00195/USCOURTS-ned-8_09-cv-00195-6/content-detail.html</url>
  <url access="raw object" displayLabel="PDF rendition">http://www.gpo.gov/fdsys/pkg/USCOURTS-ned-8_09-cv-00195/pdf/USCOURTS-ned-8_09-cv-00195-6.pdf</url>
</location>
 <extension>
  <searchTitle>USCOURTS 8:09-cv-00195; Precision Industries, Inc. v. Tyson Foods, Inc.; </searchTitle>
  <courtName>United States District Court District of Nebraska</courtName>
  <state>Nebraska</state>
  <accessId>USCOURTS-ned-8_09-cv-00195-6</accessId>
  <sequenceNumber>6</sequenceNumber>
  <dateIssued>2010-09-13</dateIssued>
  <docketText>ORDER granting 72 Motion to Compel; adopting 89 Stipulation. The defendant shall have until October 1, 2010, to supplement discovery responses. Ordered by Magistrate Judge Thomas D. Thalken. (TRL)</docketText>
</extension>
</relatedItem>
<relatedItem type="constituent" ID="id-USCOURTS-ned-8_09-cv-00195-7" xlink:href="http://www.gpo.gov/fdsys/granule/USCOURTS-ned-8_09-cv-00195/USCOURTS-ned-8_09-cv-00195-7/mods.xml">
 <titleInfo>
  <title>Precision Industries, Inc. v. Tyson Foods, Inc.</title>
  <subTitle>AMENDED PROTECTIVE ORDER adopting 131 Stipulation. Ordered by Magistrate Judge Thomas D. Thalken. (TRL)</subTitle>
  <partNumber>7</partNumber>
</titleInfo>
 <originInfo>
  <dateIssued>2010-12-09</dateIssued>
</originInfo>
 <relatedItem xlink:href="http://www.gpo.gov/fdsys/pkg/pdf/USCOURTS-ned-8_09-cv-00195-7.pdf" type="otherFormat">
  <identifier type="FDsys Unique ID">D09002ee1817fca1a</identifier>
</relatedItem>
 <identifier type="uri">http://www.gpo.gov/fdsys/granule/USCOURTS-ned-8_09-cv-00195/USCOURTS-ned-8_09-cv-00195-7</identifier>
 <identifier type="former granule identifier">ned-8_09-cv-00195_7.pdf</identifier>
 <location>
  <url access="object in context" displayLabel="Content Detail">http://www.gpo.gov/fdsys/granule/USCOURTS-ned-8_09-cv-00195/USCOURTS-ned-8_09-cv-00195-7/content-detail.html</url>
  <url access="raw object" displayLabel="PDF rendition">http://www.gpo.gov/fdsys/pkg/USCOURTS-ned-8_09-cv-00195/pdf/USCOURTS-ned-8_09-cv-00195-7.pdf</url>
</location>
 <extension>
  <searchTitle>USCOURTS 8:09-cv-00195; Precision Industries, Inc. v. Tyson Foods, Inc.; </searchTitle>
  <courtName>United States District Court District of Nebraska</courtName>
  <state>Nebraska</state>
  <accessId>USCOURTS-ned-8_09-cv-00195-7</accessId>
  <sequenceNumber>7</sequenceNumber>
  <dateIssued>2010-12-09</dateIssued>
  <docketText>AMENDED PROTECTIVE ORDER adopting 131 Stipulation. Ordered by Magistrate Judge Thomas D. Thalken. (TRL)</docketText>
</extension>
</relatedItem>
<relatedItem type="constituent" ID="id-USCOURTS-ned-8_09-cv-00195-8" xlink:href="http://www.gpo.gov/fdsys/granule/USCOURTS-ned-8_09-cv-00195/USCOURTS-ned-8_09-cv-00195-8/mods.xml">
 <titleInfo>
  <title>Precision Industries, Inc. v. Tyson Foods, Inc.</title>
  <subTitle>ORDER - The parties request for stay is granted. On or before February 4, 2011, the parties shall file a status report containing counsels position(s) concerning whether the stay should continue in effect or whether the stay should be lifted. Ordered by Magistrate Judge Thomas D. Thalken. (KBJ)</subTitle>
  <partNumber>8</partNumber>
</titleInfo>
 <originInfo>
  <dateIssued>2011-01-25</dateIssued>
</originInfo>
 <relatedItem xlink:href="http://www.gpo.gov/fdsys/pkg/pdf/USCOURTS-ned-8_09-cv-00195-8.pdf" type="otherFormat">
  <identifier type="FDsys Unique ID">D09002ee1817fcac2</identifier>
</relatedItem>
 <identifier type="uri">http://www.gpo.gov/fdsys/granule/USCOURTS-ned-8_09-cv-00195/USCOURTS-ned-8_09-cv-00195-8</identifier>
 <identifier type="former granule identifier">ned-8_09-cv-00195_8.pdf</identifier>
 <location>
  <url access="object in context" displayLabel="Content Detail">http://www.gpo.gov/fdsys/granule/USCOURTS-ned-8_09-cv-00195/USCOURTS-ned-8_09-cv-00195-8/content-detail.html</url>
  <url access="raw object" displayLabel="PDF rendition">http://www.gpo.gov/fdsys/pkg/USCOURTS-ned-8_09-cv-00195/pdf/USCOURTS-ned-8_09-cv-00195-8.pdf</url>
</location>
 <extension>
  <searchTitle>USCOURTS 8:09-cv-00195; Precision Industries, Inc. v. Tyson Foods, Inc.; </searchTitle>
  <courtName>United States District Court District of Nebraska</courtName>
  <state>Nebraska</state>
  <accessId>USCOURTS-ned-8_09-cv-00195-8</accessId>
  <sequenceNumber>8</sequenceNumber>
  <dateIssued>2011-01-25</dateIssued>
  <docketText>ORDER - The parties request for stay is granted. On or before February 4, 2011, the parties shall file a status report containing counsels position(s) concerning whether the stay should continue in effect or whether the stay should be lifted. Ordered by Magistrate Judge Thomas D. Thalken. (KBJ)</docketText>
</extension>
</relatedItem>
</mods>